cmeson/__init__.py
cmeson/__main__.py
cmeson/application.py
cmeson/command.py
cmeson/editwidgets.py
cmeson/optionlist.py
cmeson/screen.py
cmeson-2021.10.3.data/data/share/man/man1/cmeson.1
cmeson-2021.10.3.dist-info/LICENSE
cmeson-2021.10.3.dist-info/METADATA
cmeson-2021.10.3.dist-info/WHEEL
cmeson-2021.10.3.dist-info/entry_points.txt
cmeson-2021.10.3.dist-info/top_level.txt
cmeson-2021.10.3.dist-info/RECORD
