Metadata-Version: 2.1
Name: cmeson
Version: 2021.10.3
Summary: TUI for meson build system
Home-page: https://github.com/proskur1n/cmeson
Author: Andrey Proskurin (proskur1n)
Author-email: andreyproskurin@protonmail.com
License: MIT
Download-URL: https://github.com/proskur1n/cmeson/archive/2021.10.03.tar.gz
Keywords: cmeson meson build system TUI
Platform: UNKNOWN
Requires-Dist: meson (>=0.5)
Requires-Dist: urwid
